gpsdatetime/__init__.py
gpsdatetime/gpsdatetime.py
gpsdatetime-1.0.32.dist-info/LICENCE.txt
gpsdatetime-1.0.32.dist-info/METADATA
gpsdatetime-1.0.32.dist-info/WHEEL
gpsdatetime-1.0.32.dist-info/top_level.txt
gpsdatetime-1.0.32.dist-info/RECORD
