Metadata-Version: 2.1
Name: gpsdatetime
Version: 1.0.32
Summary: Python GPS date/time management package
Home-page: https://gitlab.com/jbeilin/gpsdatetime
Download-URL: https://gitlab.com/jbeilin/gpsdatetime/-/archive/v1.0.32/gpsdatetime-v1.0.32.tar.gz
Author: Jacques Beilin
Author-email: jacques.beilin@gmail.com
License-File: LICENCE.txt
